rallyio/__init__.py
rallyio/rag.py
rallyio/search.py
rallyio-0.1.3.dist-info/METADATA
rallyio-0.1.3.dist-info/WHEEL
rallyio-0.1.3.dist-info/top_level.txt
rallyio-0.1.3.dist-info/RECORD
