Metadata-Version: 2.4
Name: rallyio
Version: 0.1.3
Summary: A Python library for interacting with Rally.io services
Home-page: https://github.com/jatinarora2409/rallyio
Author: Jatin Arora
Author-email: jatinarora2409@gmail.com
Classifier: Programming Language :: Python :: 3
Classifier: Programming Language :: Python :: 3.8
Classifier: Programming Language :: Python :: 3.9
Classifier: Programming Language :: Python :: 3.10
Classifier: Programming Language :: Python :: 3.11
Classifier: License :: OSI Approved :: MIT License
Classifier: Operating System :: OS Independent
Classifier: Development Status :: 4 - Beta
Classifier: Intended Audience :: Developers
Classifier: Topic :: Software Development :: Libraries :: Python Modules
Requires-Python: >=3.8
Requires-Dist: requests>=2.31.0
Requires-Dist: google-cloud-aiplatform>=1.38.0
Requires-Dist: google-generativeai>=0.3.0
Dynamic: author
Dynamic: author-email
Dynamic: classifier
Dynamic: description
Dynamic: description-content-type
Dynamic: home-page
Dynamic: requires-dist
Dynamic: requires-python
Dynamic: summary
